{
  "inspections": [
    {
      "id": "INS-001",
      "cluster": "Cluster 2A",
      "package": 4,
      "activity": "Work at Height",
      "date": "2026-03-26",
      "status": "Critical"
    },
    {
      "id": "INS-002",
      "cluster": "Cluster 8A",
      "package": 2,
      "activity": "Scaffolding",
      "date": "2026-03-26",
      "status": "Open"
    },
    {
      "id": "INS-003",
      "cluster": "Cluster 4",
      "package": 3,
      "activity": "Edge Protection",
      "date": "2026-03-30",
      "status": "Open"
    }
  ],
  "actions": [
    {
      "id": "ACT-001",
      "status": "Open",
      "cluster": "Cluster 2A",
      "owner": "Cluster CM / PD",
      "target_date": "2026-04-02"
    },
    {
      "id": "ACT-002",
      "status": "Open",
      "cluster": "Cluster 8A",
      "owner": "CM & HSE Manager",
      "target_date": "Ongoing"
    },
    {
      "id": "ACT-003",
      "status": "Closed",
      "cluster": "Cluster 4",
      "owner": "Site Team",
      "target_date": "2026-03-31"
    }
  ]
}
